wayfound/__init__.py
wayfound/session.py
wayfound-2.5.0.dist-info/METADATA
wayfound-2.5.0.dist-info/WHEEL
wayfound-2.5.0.dist-info/top_level.txt
wayfound-2.5.0.dist-info/RECORD
