Metadata-Version: 2.4
Name: wayfound
Version: 2.5.0
Summary: Provides a simple interface for interacting with the Wayfound Manager API.
Author-email: Chad Burnette <chad@wayfound.ai>
License: MIT
Project-URL: Homepage, https://github.com/Wayfound-AI/wayfound-sdk-python
Project-URL: Issues, https://github.com/Wayfound-AI/wayfound-sdk-python/issues
Classifier: Programming Language :: Python :: 3
Classifier: Operating System :: OS Independent
Requires-Python: >=3.8
